nashx/__init__.py
nashx/hasher.py
nashx-0.2.dist-info/METADATA
nashx-0.2.dist-info/WHEEL
nashx-0.2.dist-info/entry_points.txt
nashx-0.2.dist-info/top_level.txt
nashx-0.2.dist-info/RECORD
