Metadata-Version: 2.1
Name: nashx
Version: 0.2
Summary: UNKNOWN
Home-page: https://github.com/Naman7214/NASHX.git
Author: Naman Agnihotri
Author-email: namanagnihotri280@gmail.com
License: UNKNOWN
Platform: UNKNOWN
